MANIFEST.in
plugin_thunderbird.xml
setup.py
./__init__.py
./__openerp__.py
./plugin_thunderbird.py
i18n/ar.po
i18n/bg.po
i18n/ca.po
i18n/cs.po
i18n/da.po
i18n/de.po
i18n/en_GB.po
i18n/en_US.po
i18n/es.po
i18n/es_CR.po
i18n/et.po
i18n/eu.po
i18n/fi.po
i18n/fr.po
i18n/gl.po
i18n/hr.po
i18n/hu.po
i18n/is.po
i18n/it.po
i18n/ja.po
i18n/mk.po
i18n/mn.po
i18n/nb.po
i18n/nl.po
i18n/pl.po
i18n/plugin_thunderbird.pot
i18n/pt.po
i18n/pt_BR.po
i18n/ro.po
i18n/ru.po
i18n/sk.po
i18n/sl.po
i18n/sr.po
i18n/sr@latin.po
i18n/sv.po
i18n/tr.po
i18n/zh_CN.po
images/config_thunderbird.jpeg
images/config_thunderbird_plugin.jpeg
images/thunderbird_document.jpeg
openerp_plugin_thunderbird.egg-info/PKG-INFO
openerp_plugin_thunderbird.egg-info/SOURCES.txt
openerp_plugin_thunderbird.egg-info/dependency_links.txt
openerp_plugin_thunderbird.egg-info/requires.txt
openerp_plugin_thunderbird.egg-info/top_level.txt
static/thunderbird_plugin/install.js
static/thunderbird_plugin/chrome/openerp_plugin/content/js/config.js
static/thunderbird_plugin/chrome/openerp_plugin/content/js/create.js
static/thunderbird_plugin/chrome/openerp_plugin/content/js/dialog.js
static/thunderbird_plugin/chrome/openerp_plugin/content/js/overlay.js
static/thunderbird_plugin/chrome/openerp_plugin/content/js/push.js
static/thunderbird_plugin/chrome/openerp_plugin/content/js/tiny_xmlrpc.js
static/thunderbird_plugin/chrome/openerp_plugin/content/js/tools.js
static/thunderbird_plugin/chrome/openerp_plugin/skin/Archive.png
static/thunderbird_plugin/chrome/openerp_plugin/skin/Create.png
static/thunderbird_plugin/chrome/openerp_plugin/skin/Error.gif
static/thunderbird_plugin/chrome/openerp_plugin/skin/Move.gif
static/thunderbird_plugin/chrome/openerp_plugin/skin/MoveDown.png
static/thunderbird_plugin/chrome/openerp_plugin/skin/MoveLeft.png
static/thunderbird_plugin/chrome/openerp_plugin/skin/Search.gif
static/thunderbird_plugin/chrome/openerp_plugin/skin/Success.gif
static/thunderbird_plugin/chrome/openerp_plugin/skin/developped_by.png
static/thunderbird_plugin/chrome/openerp_plugin/skin/logo.png
static/thunderbird_plugin/chrome/openerp_plugin/skin/openerp.png
static/thunderbird_plugin/chrome/openerp_plugin/skin/perform.gif
